fist/cli/__init__.py
fist/cli/__main__.py
fist/cli/add.py
fist/cli/build.py
fist/cli/main.py
fist/cli/utils.py
fist/models/__init__.py
fist/models/bundle.py
fist/models/contributor.py
fist/models/detection.py
fist/models/mitigation.py
fist/models/note.py
fist/models/phase.py
fist/models/tactic.py
fist/models/technique.py
fist/models/tool.py
fist/models/utils/__init__.py
fist/models/utils/base.py
fist/models/utils/config.py
fist/models/utils/external_reference.py
fist/models/utils/item_group.py
fist/models/utils/validator.py
fist/utils/__init__.py
fist/utils/common.py
fist/utils/parsing.py
fist/utils/sdo.py
fist/utils/vocabularies.py
fist-0.0.12.dist-info/METADATA
fist-0.0.12.dist-info/WHEEL
fist-0.0.12.dist-info/entry_points.txt
fist-0.0.12.dist-info/licenses/LICENSE
fist-0.0.12.dist-info/RECORD
