Metadata-Version: 2.4
Name: fist
Version: 0.0.12
Summary: STIX2 bundle & WIKI documentation Generator
License-File: LICENSE
Requires-Python: >=3.12
Requires-Dist: click~=8.3.0
Requires-Dist: pydantic~=2.12.4
Requires-Dist: pyyaml~=6.0.3
Requires-Dist: ruamel-yaml~=0.18.16
Requires-Dist: stix2~=3.0.1
